deepseek_client/__init__.py
deepseek_client/client.py
deepseek_client_python-1.0.3.dist-info/LICENSE
deepseek_client_python-1.0.3.dist-info/METADATA
deepseek_client_python-1.0.3.dist-info/WHEEL
deepseek_client_python-1.0.3.dist-info/RECORD
